setup.py
Products/__init__.py
Products.ZopeProfiler.egg-info/PKG-INFO
Products.ZopeProfiler.egg-info/SOURCES.txt
Products.ZopeProfiler.egg-info/dependency_links.txt
Products.ZopeProfiler.egg-info/namespace_packages.txt
Products.ZopeProfiler.egg-info/not-zip-safe
Products.ZopeProfiler.egg-info/requires.txt
Products.ZopeProfiler.egg-info/top_level.txt
Products/ZopeProfiler/HLProfiler.py
Products/ZopeProfiler/LICENSE.txt
Products/ZopeProfiler/MonkeyPatcher.py
Products/ZopeProfiler/README.txt
Products/ZopeProfiler/ZopeProfiler.py
Products/ZopeProfiler/__init__.py
Products/ZopeProfiler/showDocumentation.dtml
Products/ZopeProfiler/showStatistics.dtml
Products/ZopeProfiler/showStatus.dtml
Products/ZopeProfiler/version.txt
Products/ZopeProfiler/zprf.patch