Metadata-Version: 1.0
Name: Products.ZopeProfiler
Version: 2.0.2
Summary: Zope 2 profiler to learn what Zope spends it time on. For Zope 2.10-2.13
Home-page: http://www.dieter.handshake.de/pyprojects/zope
Author: Dieter Maurer
Author-email: dieter@handshake.de
License: BSD (see "Products/ZopeProfiler/LICENSE.txt", for details)
Keywords: Zope 2,profiling,time,analysis,caller,callee
Platform: UNKNOWN
Classifier: Development Status :: 5 - Production/Stable
Classifier: Intended Audience :: Developers
Classifier: License :: OSI Approved :: BSD License
Classifier: Framework :: Zope2
Classifier: Operating System :: OS Independent
Classifier: Programming Language :: Python
Classifier: Topic :: Utilities
